_k_means_lloyd_reg.cpython-38-x86_64-linux-gnu.so
cntools/__init__.py
cntools/smoothing/NaiveSmooth.py
cntools/smoothing/HMRF.py
cntools/smoothing/__init__.py
cntools/smoothing/base.py
cntools/utils/utils.py
cntools/utils/_k_means_lloyd_reg.pyx
cntools/utils/_k_means_lloyd_reg.c
cntools/utils/__init__.py
cntools/utils/kmeans_reg.py
cntools/datasets/make_ds.py
cntools/datasets/prep.py
cntools/datasets/__init__.py
cntools/identification/CFIDF.py
cntools/identification/Spatial_LDA.py
cntools/identification/CC.py
cntools/identification/__init__.py
cntools/identification/base.py
cntools/identification/CNE.py
cntools-2.1.11.dist-info/LICENSE
cntools-2.1.11.dist-info/METADATA
cntools-2.1.11.dist-info/RECORD
cntools-2.1.11.dist-info/top_level.txt
cntools-2.1.11.dist-info/WHEEL
