Metadata-Version: 2.1
Name: cntools
Version: 2.1.11
Summary: A package for identifying cellular neighborhoods
Author-email: Yicheng Tao <yctao@umich.edu>
Maintainer-email: Yicheng Tao <yctao@umich.edu>
License: MIT License
Project-URL: Homepage, https://github.com/liu-bioinfo-lab/CNTools
Project-URL: Issues, https://github.com/liu-bioinfo-lab/CNTools/issues
Keywords: cellular neighborhoods
Classifier: Topic :: Scientific/Engineering :: Bio-Informatics
Classifier: Development Status :: 3 - Alpha
Classifier: License :: OSI Approved :: MIT License
Classifier: Programming Language :: Python :: 3
Classifier: Operating System :: OS Independent
Classifier: Intended Audience :: Science/Research
Requires-Python: >=3.8
License-File: LICENSE
Requires-Dist: cython ==0.29.36
Requires-Dist: gdown ==5.1.0
Requires-Dist: jupyter ==1.0.0
Requires-Dist: matplotlib ==3.4.2
Requires-Dist: networkx ==2.6.2
Requires-Dist: numpy ==1.20.3
Requires-Dist: pandas ==1.2.4
Requires-Dist: pip ==23.2.1
Requires-Dist: pillow ==10.3.0
Requires-Dist: pydot ==1.4.2
Requires-Dist: python-louvain ==0.15
Requires-Dist: scikit-learn ==0.24.2
Requires-Dist: scipy ==1.6.2
Requires-Dist: seaborn ==0.11.2
Requires-Dist: shapely ==1.8.4
Requires-Dist: statsmodels ==0.12.2
Requires-Dist: tensorly ==0.5.1
Requires-Dist: tqdm ==4.62.1
Requires-Dist: spatial-lda ==0.1.3
